trysts/__init__.py
trysts/__objectives/OSM/OSM.S.HTML
trysts/__objectives/objectives.S.HTML
trysts/_licenses/gpl-3.0-standalone.html
trysts/_ops/_clique/__init__.py
trysts/_ops/_clique/group/__init__.py
trysts/_status/DB/records.json
trysts/_status/monitors/status_1.py
trysts/_status/status.proc.py
trysts/adventures/sanique/public/assets/AboutView-B_a93Z7o.js
trysts/adventures/sanique/public/assets/AboutView-C6Dx7pxG.css
trysts/adventures/sanique/public/assets/index-C7uNmA4t.js
trysts/adventures/sanique/public/assets/index-DHqK1tyo.css
trysts/adventures/sanique/public/index.html
trysts/adventures/sanique/public/typescript.svg
trysts/adventures/sanique/public/vite.svg
trysts/adventures/stack.S.HTML
trysts/besties/OSM/OSM.S.HTML
trysts/license.S.HTML
trysts/mixer.MD
trysts/mixer.S.HTML
trysts-0.0.2.dist-info/METADATA
trysts-0.0.2.dist-info/WHEEL
trysts-0.0.2.dist-info/entry_points.txt
trysts-0.0.2.dist-info/RECORD
